dictcruncher
